sw4rm/__init__.py
sw4rm/ack_integration.py
sw4rm/acks.py
sw4rm/activity_buffer.py
sw4rm/buffer_strategy.py
sw4rm/cli.py
sw4rm/config.py
sw4rm/constants.py
sw4rm/content_types.py
sw4rm/envelope.py
sw4rm/error_mapping.py
sw4rm/exceptions.py
sw4rm/feature_flags.py
sw4rm/interceptors.py
sw4rm/logging.py
sw4rm/metrics.py
sw4rm/negotiation_coordinator.py
sw4rm/negotiation_events.py
sw4rm/negotiation_types.py
sw4rm/persistence.py
sw4rm/policy_store.py
sw4rm/policy_types.py
sw4rm/shared_context.py
sw4rm/tracing.py
sw4rm/worktree_policies.py
sw4rm/worktree_state.py
sw4rm/audit/__init__.py
sw4rm/audit/interface.py
sw4rm/audit/types.py
sw4rm/audit/verification.py
sw4rm/clients/__init__.py
sw4rm/clients/activity.py
sw4rm/clients/connector.py
sw4rm/clients/hitl.py
sw4rm/clients/logging.py
sw4rm/clients/negotiation.py
sw4rm/clients/negotiation_room.py
sw4rm/clients/reasoning.py
sw4rm/clients/registry.py
sw4rm/clients/router.py
sw4rm/clients/scheduler.py
sw4rm/clients/scheduler_policy.py
sw4rm/clients/tool.py
sw4rm/clients/worktree.py
sw4rm/handoff/__init__.py
sw4rm/handoff/client.py
sw4rm/handoff/context.py
sw4rm/handoff/types.py
sw4rm/llm/__init__.py
sw4rm/llm/claude_sdk.py
sw4rm/llm/client.py
sw4rm/llm/factory.py
sw4rm/llm/mock.py
sw4rm/runtime/agent.py
sw4rm/secrets/__init__.py
sw4rm/secrets/backend.py
sw4rm/secrets/cli.py
sw4rm/secrets/errors.py
sw4rm/secrets/factory.py
sw4rm/secrets/resolver.py
sw4rm/secrets/types.py
sw4rm/secrets/backends/file_backend.py
sw4rm/secrets/backends/keyring_backend.py
sw4rm/voting/__init__.py
sw4rm/voting/aggregation.py
sw4rm/voting/strategies.py
sw4rm/workflow/__init__.py
sw4rm/workflow/builder.py
sw4rm/workflow/engine.py
sw4rm/workflow/example.py
sw4rm/workflow/types.py
sw4rm_sdk-0.4.0.dist-info/licenses/LICENSE
sw4rm_sdk-0.4.0.dist-info/METADATA
sw4rm_sdk-0.4.0.dist-info/WHEEL
sw4rm_sdk-0.4.0.dist-info/entry_points.txt
sw4rm_sdk-0.4.0.dist-info/top_level.txt
sw4rm_sdk-0.4.0.dist-info/RECORD
