Metadata-Version: 2.4
Name: sw4rm-sdk
Version: 0.4.0
Summary: SW4RM Agentic Protocol — Reference Python SDK (experimental)
Author: SW4RM Devs
License: Apache-2.0
Project-URL: Homepage, https://sw4rm.ai
Project-URL: Source, https://sw4rm.ai/repo
Requires-Python: >=3.9
License-File: LICENSE
Requires-Dist: protobuf<5,>=4.23
Requires-Dist: grpcio<2,>=1.56
Requires-Dist: googleapis-common-protos<2,>=1.60
Provides-Extra: dev
Requires-Dist: grpcio-tools<2,>=1.56; extra == "dev"
Requires-Dist: build<2,>=1.0; extra == "dev"
Requires-Dist: twine<6,>=5; extra == "dev"
Requires-Dist: pkginfo<2,>=1.10; extra == "dev"
Provides-Extra: docs
Requires-Dist: mkdocs>=1.5.0; extra == "docs"
Requires-Dist: mkdocs-material>=9.4.0; extra == "docs"
Requires-Dist: mkdocs-gen-files>=0.5.0; extra == "docs"
Requires-Dist: mkdocs-literate-nav>=0.6.0; extra == "docs"
Requires-Dist: mkdocs-section-index>=0.3.0; extra == "docs"
Requires-Dist: mkdocstrings[python]>=0.24.0; extra == "docs"
Requires-Dist: mkdocs-htmlproofer-plugin>=0.13.0; extra == "docs"
Requires-Dist: mkdocs-kroki-plugin>=0.8.0; extra == "docs"
Dynamic: license-file
